fenlmagic/__init__.py
fenlmagic-0.0.19.dist-info/LICENSE
fenlmagic-0.0.19.dist-info/METADATA
fenlmagic-0.0.19.dist-info/WHEEL
fenlmagic-0.0.19.dist-info/top_level.txt
fenlmagic-0.0.19.dist-info/RECORD
