Metadata-Version: 2.1
Name: fenlmagic
Version: 0.0.19
Summary: An IPython extension for executing Fenl
Home-page: https://kaskada.com
Author: Kaskada
Author-email: support@kaskada.com
Project-URL: Documentation, https://docs.kaskada.com
Classifier: Development Status :: 3 - Alpha
Classifier: Framework :: Jupyter
Classifier: Programming Language :: Python :: 3
Classifier: License :: Other/Proprietary License
Requires-Python: >=3.6
License-File: LICENSE
Requires-Dist: kaskada (==0.0.22)
Requires-Dist: kaskada-grpc
